LICENSE.txt
README.rst
setup.cfg
setup.py
cyclotron_aiokafka/__init__.py
cyclotron_aiokafka/asyncio.py
cyclotron_aiokafka/consumer.py
cyclotron_aiokafka/kafka.py
cyclotron_aiokafka.egg-info/PKG-INFO
cyclotron_aiokafka.egg-info/SOURCES.txt
cyclotron_aiokafka.egg-info/dependency_links.txt
cyclotron_aiokafka.egg-info/requires.txt
cyclotron_aiokafka.egg-info/top_level.txt
tests/__init__.py
tests/test_stub.py