Metadata-Version: 1.1
Name: cyclotron-aiokafka
Version: 0.5.0
Summary: AioKafka driver for cyclotron
Home-page: https://github.com/MainRo/cyclotron-aiokafka.git
Author: Romain Picard
Author-email: romain.picard@oakbits.com
License: MIT
Platform: any
Classifier: Development Status :: 3 - Alpha
Classifier: License :: OSI Approved :: MIT License
Classifier: Intended Audience :: Developers
Classifier: Programming Language :: Python :: 3
